[
  {
    "id": 0,
    "lat": 52.48025619114025,
    "lng": 13.448806546002196,
    "category": "ERRANDS",
    "status": "QUARANTINED",
    "isVulnerable": false
  },
  {
    "id": 1,
    "lat": 52.48179824340709,
    "lng": 13.447776577740477,
    "category": "DRIVING",
    "status": "VOLUNTARILY_SELF_ISOLATED",
    "isVulnerable": false
  },
  {
    "id": 2,
    "lat": 52.48319649831199,
    "lng": 13.45269038465576,
    "category": "CONTACT",
    "status": "VOLUNTARILY_SELF_ISOLATED",
    "isVulnerable": true
  },
  {
    "id": 3,
    "lat": 52.48250391031573,
    "lng": 13.446574948101805,
    "category": "DOG_WALKING",
    "status": "QUARANTINED",
    "isVulnerable": true
  },
  {
    "id": 4,
    "lat": 52.48102722402994,
    "lng": 13.458162091046141,
    "category": "GROCCERIES",
    "status": "INFECTED",
    "isVulnerable": true
  },
  {
    "id": 5,
    "lat": 52.47847884351453,
    "lng": 13.454063675671385,
    "category": "GROCCERIES",
    "status": "INFECTED",
    "isVulnerable": true
  },
  {
    "id": 6,
    "lat": 52.47866180908524,
    "lng": 13.449149868756102,
    "category": "GROCCERIES",
    "status": "INFECTED",
    "isVulnerable": true
  },
  {
    "id": 7,
    "lat": 52.47939366375959,
    "lng": 13.44569518354492,
    "category": "GROCCERIES",
    "status": "INFECTED",
    "isVulnerable": true
  },
  {
    "id": 8,
    "lat": 52.48179824340709,
    "lng": 13.459985993176268,
    "category": "GROCCERIES",
    "status": "INFECTED",
    "isVulnerable": true
  },
  {
    "id": 9,
    "lat": 52.48311809267103,
    "lng": 13.450308583050536,
    "category": "GROCCERIES",
    "status": "INFECTED",
    "isVulnerable": true
  },
  {
    "id": 10,
    "lat": 52.47905387560328,
    "lng": 13.453548691540526,
    "category": "GROCCERIES",
    "status": "INFECTED",
    "isVulnerable": true
  },
  {
    "id": 11,
    "lat": 52.47962890017672,
    "lng": 13.459063313275145,
    "category": "GROCCERIES",
    "status": "INFECTED",
    "isVulnerable": true
  }
]
